stratus/__init__.py
stratus/handlers/__init__.py
stratus/handlers/endpoint.py
stratus_endpoint-0.0.2.dist-info/LICENSE
stratus_endpoint-0.0.2.dist-info/METADATA
stratus_endpoint-0.0.2.dist-info/WHEEL
stratus_endpoint-0.0.2.dist-info/top_level.txt
stratus_endpoint-0.0.2.dist-info/RECORD
