Metadata-Version: 2.1
Name: stratus-endpoint
Version: 0.0.2
Summary: Base classes for creating service endpoints for the Stratus Framework
Home-page: https://github.com/nasa-nccs-cds/stratus-endpoint
Author: Thomas Maxwell
Author-email: thomas.maxwell@nasa.gov
License: UNKNOWN
Platform: UNKNOWN
Classifier: Programming Language :: Python :: 3
Classifier: License :: OSI Approved :: MIT License
Classifier: Operating System :: OS Independent
